{"name":"Net-salesforce-client","tagline":"Perl interface to Salesforce.com JSON api","body":"# NAME\r\n\r\nNet::Salesforce::Client - Salesforce.com client utilities\r\n\r\n# SYNOPSIS\r\n\r\n    use Net::Salesforce::Client;\r\n\r\n# DESCRIPTION\r\n\r\nNet::Salesforce::Client is a perl interface to Salesforce.com JSON api.\r\n\r\n# ATTRIBUTES\r\n\r\n## access\\_token\r\n\r\nAccess token received from authenticating with [Net::Salesforce](https://metacpan.org/pod/Net::Salesforce).\r\n\r\n## api\\_version\r\n\r\nCurrent supported API version from Salesforce\r\n\r\n## api\\_host\r\n\r\nSalesforce domain where your application lives, e.g. Developer force usually uses\r\n\r\n    https://na17.salesforce.com/\r\n\r\n## ua\r\n\r\nA [Mojo::UserAgent](https://metacpan.org/pod/Mojo::UserAgent) object.\r\n\r\n## json\r\n\r\nA [Mojo::JSON](https://metacpan.org/pod/Mojo::JSON) object.\r\n\r\n# METHODS\r\n\r\n## api\\_url\r\n\r\nSalesforce API url for accessing sobjects\r\n\r\n## model\r\n\r\nSelect model namespace you wish to query, e.g. 'Account'\r\n\r\n## sobjects\r\n\r\nRetrieve list of available sobjects\r\n\r\n## get\r\n\r\nPerform authenticated requests against Salesforce API\r\n\r\n# INSTALL\r\n\r\n    $ cpanm git://github.com/battlemidget/Net-Salesforce-Client.git\r\n\r\nIf you'd wish to try out the latest code base you can do so with above\r\ncommand.\r\n\r\n# AUTHOR\r\n\r\nAdam Stokes <adamjs@cpan.org>\r\n\r\n# COPYRIGHT\r\n\r\nCopyright 2014- Adam Stokes\r\n\r\n# LICENSE\r\n\r\nThis library is free software; you can redistribute it and/or modify\r\nit under the same terms as Perl itself.\r\n\r\n# SEE ALSO\r\n","google":"","note":"Don't delete this file! It's used internally to help with page regeneration."}